yummly-0.5.0.dist-info/METADATA
yummly-0.5.0.dist-info/DESCRIPTION.rst
yummly-0.5.0.dist-info/metadata.json
yummly-0.5.0.dist-info/top_level.txt
yummly-0.5.0.dist-info/WHEEL
yummly-0.5.0.dist-info/RECORD
yummly/client.py
yummly/__init__.py
yummly/models.py
yummly/__meta__.py
