Metadata-Version: 2.0
Name: yummly
Version: 0.5.0
Summary: Python library for Yummly API: https://developer.yummly.com
Home-page: https://github.com/dgilland/yummly.py
Author: Derrick Gilland
Author-email: dgilland@gmail.com
License: MIT License
Platform: UNKNOWN
Classifier: Environment :: Web Environment
Classifier: Intended Audience :: Developers
Classifier: Operating System :: OS Independent
Classifier: Programming Language :: Python
Classifier: License :: OSI Approved :: MIT License
Requires-Dist: requests (>=1.1.0)
